[
  {
    "loadType": "user",
    "username": "HOS USA",
    "name": { "first": "Jerri", "last": "Johnson" },
    "email": "Megagamesareamazing@gmail.com",
    "phone": "9167584621",
    "password": "PWtest",
    "address": {
      "street1": "458 Rosebud Way",
      "street2": "",
      "city": "Rosefield",
      "state": "CA",
      "zipcode": "97534"
    },
    "dob": "1997-12-08",
    "gender": "Female",
    "discord": "Rawr",
    "teamCode": "USA",
    "roles": ["Player"]
  },
  {
    "loadType": "user",
    "username": "HOS UK",
    "name": { "first": "Lisa", "last": "Frank" },
    "email": "Art@gmail.com",
    "phone": "9167584625",
    "password": "PWTest",
    "address": {
      "street1": "15 Craft way",
      "street2": "",
      "city": "Zoo",
      "state": "AZ",
      "zipcode": "12345"
    },
    "dob": "1992-08-03",
    "gender": "Non-Binary",
    "discord": "Pretty",
    "teamCode": "TUK",
    "roles": ["Player"]
  },
  {
    "loadType": "user",
    "username": "HOS RSA",
    "name": { "first": "Nelson", "last": "M." },
    "email": "SAfortheWin@gmail.com",
    "phone": "9161234567",
    "password": "PWtest",
    "address": {
      "street1": "785 Easy St",
      "street2": "",
      "city": "Luxury Town",
      "state": "CA",
      "zipcode": "45792"
    },
    "dob": "1994-05-08",
    "gender": "Female",
    "discord": "Money",
    "teamCode": "RSA",
    "roles": ["Player"]
  },
  {
    "loadType": "user",
    "username": "HOS Russia",
    "name": { "first": "Patricia", "last": "Doors" },
    "email": "PRlevelsStartAt5@gmail.com",
    "phone": "9167584622",
    "password": "PWtest",
    "address": {
      "street1": "856 Easy St",
      "street2": "",
      "city": "Luxury Town",
      "state": "CA",
      "zipcode": "45792"
    },
    "dob": "1994-05-08",
    "gender": "Female",
    "discord": "Money",
    "teamCode": "RFD",
    "roles": ["Player"]
  },
  {
    "loadType": "user",
    "username": "HOS Japan",
    "name": { "first": "Ellis", "last": "Doors" },
    "email": "oneOfThe12@gmail.com",
    "phone": "9164584622",
    "password": "PWtest",
    "address": {
      "street1": "700 Easy St",
      "street2": "",
      "city": "Luxury Town",
      "state": "CA",
      "zipcode": "45792"
    },
    "dob": "1994-05-08",
    "gender": "Female",
    "discord": "Money",
    "teamCode": "JPN",
    "roles": ["Player"]
  },
  {
    "loadType": "user",
    "username": "HOS Iran",
    "name": { "first": "Seeker", "last": "Doors" },
    "email": "wehavenukes5@gmail.com",
    "phone": "9167581111",
    "password": "PWtest",
    "address": {
      "street1": "800 Easy St",
      "street2": "",
      "city": "Luxury Town",
      "state": "CA",
      "zipcode": "45792"
    },
    "dob": "1994-05-08",
    "gender": "Female",
    "discord": "Money",
    "teamCode": "IRN",
    "roles": ["Player"]
  },
  {
    "loadType": "user",
    "username": "HOS India",
    "name": { "first": "Mary", "last": "Doors" },
    "email": "player@gmail.com",
    "phone": "9167584622",
    "password": "PWtest",
    "address": {
      "street1": "900 Easy St",
      "street2": "",
      "city": "Luxury Town",
      "state": "CA",
      "zipcode": "45792"
    },
    "dob": "1994-05-08",
    "gender": "Female",
    "discord": "Money",
    "teamCode": "IND",
    "roles": ["Player"]
  },
  {
    "loadType": "user",
    "username": "HOS France",
    "name": { "first": "Romeo", "last": "Davison" },
    "email": "LoveBeforeAll@yahoo.com",
    "phone": "9167584624",
    "password": "PWtest",
    "address": {
      "street1": "523 Come With Me way",
      "street2": "",
      "city": "Paris",
      "state": "NA",
      "zipcode": "45766"
    },
    "dob": "1994-03-12",
    "gender": "Non-Binary",
    "discord": "Free",
    "teamCode": "TFR",
    "roles": ["Player"]
  },
  {
    "loadType": "user",
    "username": "HOS Egypt",
    "name": { "first": "Ancient", "last": "Doors" },
    "email": "Ancient@yahoo.com",
    "phone": "9167700624",
    "password": "PWtest",
    "address": {
      "street1": "1000 Easy St",
      "street2": "",
      "city": "Luxury Town",
      "state": "CA",
      "zipcode": "45792"
    },
    "dob": "1994-03-12",
    "gender": "Non-Binary",
    "discord": "Free",
    "teamCode": "EPT",
    "roles": ["Player"]
  },
  {
    "loadType": "user",
    "username": "HOS China",
    "name": { "first": "George", "last": "Of the Jungle" },
    "email": "FastAsICanBe@hotmail.com",
    "phone": "9167584623",
    "password": "PWtest",
    "address": {
      "street1": "9540 Mt. Access Road",
      "street2": "",
      "city": "Hang Town",
      "state": "CA",
      "zipcode": "64825"
    },
    "dob": "2013-10-03",
    "gender": "Male",
    "discord": "Jungle",
    "teamCode": "PRC",
    "roles": ["Player"]
  },
  {
    "loadType": "user",
    "username": "HOS Brazil",
    "name": { "first": "Mano", "last": "Doors" },
    "email": "LatinAmerica@gmail.com",
    "phone": "9167584444",
    "password": "PWtest",
    "address": {
      "street1": "1100 Easy St",
      "street2": "",
      "city": "Luxury Town",
      "state": "CA",
      "zipcode": "45792"
    },
    "dob": "1994-05-08",
    "gender": "Female",
    "discord": "Money",
    "teamCode": "BRZ",
    "roles": ["Player"]
  },
  {
    "loadType": "user",
    "username": "HOS AUS",
    "name": { "first": "Sue", "last": "Doors" },
    "email": "SueDoors@gmail.com",
    "phone": "9167585555",
    "password": "PWtest",
    "address": {
      "street1": "500 Easy St",
      "street2": "",
      "city": "Luxury Town",
      "state": "CA",
      "zipcode": "45792"
    },
    "dob": "1994-05-08",
    "gender": "Female",
    "discord": "Money2",
    "teamCode": "AUS",
    "roles": ["Player"]
  },
  {
    "loadType": "user",
    "username": "HOS Fed",
    "name": { "first": "Unknown", "last": "Unknown" },
    "email": "Arty2@gmail.com",
    "phone": "9167584630",
    "password": "PWTest",
    "address": {
      "street1": "2nd st",
      "street2": "",
      "city": "Base Camp",
      "state": "AQ",
      "zipcode": "12345"
    },
    "dob": "1987-09-06",
    "gender": "Non-Binary",
    "discord": "Federation",
    "teamCode": "FFG",
    "roles": ["Player"]
  },
  {
    "loadType": "user",
    "username": "FroBoyX",
    "name": { "first": "John", "last": "Cleveland" },
    "email": "John.Cleveland@westcoastmegagames.com",
    "phone": "9167100596",
    "password": "FroBoyX",
    "address": {
      "street1": "5240 Rita Ave",
      "street2": "",
      "city": "Carmichael",
      "state": "CA",
      "zipcode": "95608"
    },
    "dob": "1986-12-03",
    "gender": "Male",
    "discord": "FroBoyX#9805",
    "teamCode": "USA",
    "roles": ["Admin", "Control", "Player"]
  },
  {
    "loadType": "user",
    "username": "spearson",
    "name": { "first": "Shawn", "last": "Pearson" },
    "email": "illuminus@gmail.com",
    "phone": "5555555555",
    "password": "TempPassword",
    "address": {
      "street1": "One Place",
      "street2": "",
      "city": "Sacramento",
      "state": "CA",
      "zipcode": "11111"
    },
    "dob": "1974-12-29",
    "gender": "Male",
    "discord": "illuminus#9763",
    "teamCode": "USA",
    "roles": ["Control", "Player"]
  },
  {
    "loadType": "user",
    "username": "eshen",
    "name": { "first": "Eric", "last": "Shen" },
    "email": "eric_shen@sbcglobal.net",
    "phone": "5555555555",
    "password": "TempPassword",
    "address": {
      "street1": "Two Place",
      "street2": "",
      "city": "Sacramento",
      "state": "CA",
      "zipcode": "11111"
    },
    "dob": "1966-10-15",
    "gender": "Male",
    "discord": "eshen#4992",
    "teamCode": "TUK",
    "roles": ["Control", "Player"]
  },
  {
    "loadType": "user",
    "username": "drewwww",
    "name": { "first": "Drew", "last": "Pascoal" },
    "email": "drewwwwdotcom@yahoo.com",
    "phone": "5555555555",
    "password": "TempPassword",
    "address": {
      "street1": "Three Place",
      "street2": "",
      "city": "Sacramento",
      "state": "CA",
      "zipcode": "11111"
    },
    "dob": "1975-04-05",
    "gender": "Male",
    "discord": "Drewwww#8011",
    "teamCode": "TUK",
    "roles": ["Control", "Player"]
  },
  {
    "loadType": "user",
    "username": "ControlMan",
    "name": { "first": "Control", "last": "Man" },
    "email": "control@gmail.com",
    "phone": "5555555555",
    "password": "TempPassword",
    "address": {
      "street1": "Four Place",
      "street2": "",
      "city": "Sacramento",
      "state": "CA",
      "zipcode": "11111"
    },
    "dob": "1974-12-29",
    "gender": "Male",
    "discord": "control#9763",
    "teamCode": "TCN",
    "roles": ["Control", "Player"]
  },
  {
    "loadType": "user",
    "username": "BobtheNinjaMan",
    "name": { "first": "Scott", "last": "McMann" },
    "email": "smcmann42@gmail.com",
    "phone": "9252653724",
    "password": "Zilster42",
    "address": {
      "street1": "3135 Ameno Road",
      "street2": "",
      "city": "Concord",
      "state": "CA",
      "zipcode": "94519"
    },
    "dob": "1994-06-30",
    "gender": "Male",
    "discord": "BobtheNinjaMan#4242",
    "teamCode": "AUS",
    "roles": ["Control", "Player"]
  },
  {
    "loadType": "user",
    "username": "Jarred",
    "name": { "first": "Jarred", "last": "Caldwell" },
    "email": "jdcaldwell1980@gmail.com",
    "phone": "9167788150",
    "password": "sagan",
    "address": {
      "street1": "4041 Bunker Hill Dr",
      "street2": "",
      "city": "Shingle Springs",
      "state": "CA",
      "zipcode": "95682"
    },
    "dob": "1980-03-05",
    "gender": "Male",
    "discord": "bookrat#3468",
    "teamCode": "USA",
    "roles": ["Control", "Player"]
  },
  {
    "loadType": "user",
    "username": "BardCicero",
    "name": { "first": "Mike", "last": "Bowles" },
    "email": "mjb235@gmail.com",
    "phone": "2099141120",
    "password": "BardCicero",
    "address": {
      "street1": "2909 Stonecreek Dr",
      "street2": "",
      "city": "Sacramento",
      "state": "CA",
      "zipcode": "95833"
    },
    "dob": "1989-08-23",
    "gender": "Male",
    "discord": "BardCicero#2241",
    "teamCode": "RFD",
    "roles": ["Control", "Player"]
  },
  {
    "loadType": "user",
    "username": "Goldfox64",
    "name": { "first": "Cody", "last": "S" },
    "email": "Goldfox64@gmail.com",
    "phone": "1111111111",
    "password": "WCMPassword#1",
    "address": {
      "street1": "The",
      "street2": "Moon",
      "city": "Earth",
      "state": "OH",
      "zipcode": "11111"
    },
    "dob": "1991-01-01",
    "gender": "Male",
    "discord": "Goldfox64#9723",
    "teamCode": "JPN",
    "roles": ["Player"]
  },
  {
    "loadType": "user",
    "username": "TheWindowtree",
    "name": { "first": "Ben", "last": "Davies" },
    "email": "dummy@gmail.com",
    "phone": "5555555555",
    "password": "Bristol100",
    "address": {
      "street1": "1 To Many",
      "street2": "",
      "city": "Bristol",
      "state": "UK",
      "zipcode": "11111"
    },
    "dob": "1991-01-01",
    "gender": "Male",
    "discord": "BenD#5491",
    "teamCode": "JPN",
    "roles": ["Player"]
  },
  {
    "loadType": "user",
    "username": "Naughtkris",
    "name": { "first": "Chris", "last": "Chesher" },
    "email": "naughtkris@yahoo.ca",
    "phone": "9022932903",
    "password": "topsecret123",
    "address": {
      "street1": "79 brian drive",
      "street2": "[]",
      "city": "Dartmouth",
      "state": "NS",
      "zipcode": "b2w 3n2"
    },
    "dob": "1976-09-22",
    "gender": "Male",
    "discord": "Naughtkris",
    "teamCode": "EPT",
    "roles": ["Player"]
  },
  {
    "loadType": "user",
    "username": "Exodus",
    "name": { "first": "Christian", "last": "Z" },
    "email": "dummy2@gmail.com",
    "phone": "5555555556",
    "password": "Aester",
    "address": {
      "street1": "2 Too Many",
      "street2": "",
      "city": "Nowhere",
      "state": "KY",
      "zipcode": "11111"
    },
    "dob": "1991-01-01",
    "gender": "Male",
    "discord": "Exodus#4041",
    "teamCode": "AUS",
    "roles": ["Player"]
  },
  {
    "username" : "Hella",
     "name" : {"first" : "Pete", "last" : "LAST NAME HERE" },
     "email" : "definitelynothella@gmail.com",
     "phone" : "PHONE NUMBER HERE",
     "password" : "Carbon14",
     "address" : 
         {"street1" : "STREET ADDRESS 1 HERE",
          "street2" : "STREET ADDRESS 2 HERE",
          "city" : "CITY HERE",
          "state" : "STATE HERE",
          "zipcode" : "ZIPCODE HERE"},
     "dob" : "YYYY-MM-DD",
     "gender" : "Male",
     "discord" : "Hella#6072",
     "teamCode" : "TUK",
     "roles": ["Player"]
 },
 {
  "username" : "RossM",
   "name" : {"first" : "FIRST NAME HERE", "last" : "LAST NAME HERE" },
   "email" : "EMAIL HERE",
   "phone" : "PHONE NUMBER HERE",
   "password" : "Space1999",
   "address" : 
       {"street1" : "STREET ADDRESS 1 HERE",
        "street2" : "STREET ADDRESS 2 HERE",
        "city" : "CITY HERE",
        "state" : "STATE HERE",
        "zipcode" : "ZIPCODE HERE"},
   "dob" : "YYYY-MM-DD",
   "gender" : "",
   "discord" : "SCREENAME#----",
   "teamCode" : "TUK",
   "roles": ["Player"]
}
]
