[
  {
    "model": "Squad",
    "name": "FFG Raid Squad 1",
    "team": "FFG",
    "country": "F1",
    "origin": "FFGBA",
    "type": "Raid"
  },
  {
    "model": "Squad",
    "name": "FFG Raid Squad 2",
    "team": "FFG",
    "country": "F1",
    "origin": "FFGBB",
    "type": "Raid"
  },
  {
    "model": "Squad",
    "name": "FFG Raid Squad 3",
    "team": "FFG",
    "country": "F1",
    "origin": "FFGBA",
    "type": "Raid"
  },
  {
    "model": "Squad",
    "name": "FFG Assault Squad 1",
    "team": "FFG",
    "country": "F1",
    "origin": "FFGBA",
    "type": "Assault"
  },
  {
    "model": "Squad",
    "name": "FFG Assault Squad 2",
    "team": "FFG",
    "country": "F1",
    "origin": "FFGBB",
    "type": "Assault"
  },
  {
    "model": "Squad",
    "name": "FFG Assault Squad 3",
    "team": "FFG",
    "country": "F1",
    "origin": "FFGBA",
    "type": "Assault"
  },
  {
    "model": "Squad",
    "name": "FFG Infiltration Squad 1",
    "team": "FFG",
    "country": "F1",
    "origin": "FFGBA",
    "type": "Infiltration"
  },
  {
    "model": "Squad",
    "name": "FFG Infiltration Squad 2",
    "team": "FFG",
    "country": "F1",
    "origin": "FFGBB",
    "type": "Infiltration"
  },
  {
    "model": "Squad",
    "name": "FFG Infiltration Squad 3",
    "team": "FFG",
    "country": "F1",
    "origin": "FFGBB",
    "type": "Infiltration"
  },
  {
    "model": "Squad",
    "name": "FFG Envoy Squad 1",
    "team": "FFG",
    "country": "F1",
    "origin": "FFGBA",
    "type": "Envoy"
  },
  {
    "model": "Squad",
    "name": "FFG Envoy Squad 2",
    "team": "FFG",
    "country": "F1",
    "origin": "FFGBB",
    "type": "Envoy"
  },
  {
    "model": "Squad",
    "name": "FFG Envoy Squad 3",
    "team": "FFG",
    "country": "F1",
    "origin": "FFGBB",
    "type": "Envoy"
  },
  {
    "model": "Squad",
    "name": "FFG Science Squad 1",
    "team": "FFG",
    "country": "F1",
    "origin": "FFGBA",
    "type": "Science"
  },
  {
    "model": "Squad",
    "name": "FFG Science Squad 2",
    "team": "FFG",
    "country": "F1",
    "origin": "FFGBB",
    "type": "Science"
  },
  {
    "model": "Squad",
    "name": "FFG Science Squad 3",
    "team": "FFG",
    "country": "F1",
    "origin": "FFGBA",
    "type": "Science"
  }
]
